inxi/inxi.py
inxi-0.1.2.dist-info/WHEEL
inxi-0.1.2.dist-info/METADATA
inxi-0.1.2.dist-info/RECORD
